limmer/ANSIUtils.py
limmer/__init__.py
limmer/ansi_styles.py
limmer/basics.py
limmer/events.py
limmer/styles.py
limmer-0.2.3.dist-info/LICENSE
limmer-0.2.3.dist-info/METADATA
limmer-0.2.3.dist-info/WHEEL
limmer-0.2.3.dist-info/top_level.txt
limmer-0.2.3.dist-info/RECORD
